recipe_executor/config.py
recipe_executor/context.py
recipe_executor/executor.py
recipe_executor/logger.py
recipe_executor/main.py
recipe_executor/models.py
recipe_executor/protocols.py
recipe_executor/llm_utils/azure_openai.py
recipe_executor/llm_utils/azure_responses.py
recipe_executor/llm_utils/llm.py
recipe_executor/llm_utils/mcp.py
recipe_executor/llm_utils/responses.py
recipe_executor/steps/__init__.py
recipe_executor/steps/base.py
recipe_executor/steps/conditional.py
recipe_executor/steps/execute_recipe.py
recipe_executor/steps/llm_generate.py
recipe_executor/steps/loop.py
recipe_executor/steps/mcp.py
recipe_executor/steps/parallel.py
recipe_executor/steps/read_files.py
recipe_executor/steps/registry.py
recipe_executor/steps/set_context.py
recipe_executor/steps/write_files.py
recipe_executor/utils/models.py
recipe_executor/utils/templates.py
recipe_executor-0.1.3.dist-info/METADATA
recipe_executor-0.1.3.dist-info/WHEEL
recipe_executor-0.1.3.dist-info/entry_points.txt
recipe_executor-0.1.3.dist-info/RECORD
